funny_excuses/__init__.py
funny_excuses-0.1.dist-info/licenses/LICENSE
funny_excuses-0.1.dist-info/METADATA
funny_excuses-0.1.dist-info/WHEEL
funny_excuses-0.1.dist-info/top_level.txt
funny_excuses-0.1.dist-info/RECORD
