Metadata-Version: 2.4
Name: funny_excuses
Version: 0.1
Summary: A funny excuse generator for everyday life.
Author: Kamran Ahmed
Author-email: your.email@example.com
Keywords: funny,excuses,humor,generator
Classifier: Programming Language :: Python :: 3
Classifier: Intended Audience :: Developers
Classifier: License :: OSI Approved :: MIT License
License-File: LICENSE
Dynamic: author
Dynamic: author-email
Dynamic: classifier
Dynamic: keywords
Dynamic: license-file
Dynamic: summary
